pasio/__init__.py
pasio/__main__.py
pasio/cached_log.py
pasio/cli.py
pasio/log_marginal_likelyhood.py
pasio/logging.py
pasio/process_bedgraph.py
pasio/segmentation.py
pasio/version.py
pasio/dto/__init__.py
pasio/dto/intervals.py
pasio/dto/sliding_window.py
pasio/splitters/__init__.py
pasio/splitters/constants_reducer.py
pasio/splitters/default_splitters.py
pasio/splitters/nop_splitter.py
pasio/splitters/reducer_combiner.py
pasio/splitters/round_reducer.py
pasio/splitters/sliding_window_reducer.py
pasio/splitters/square_splitter.py
pasio/utils/__init__.py
pasio/utils/gzip_utils.py
pasio/utils/slice_when.py
pasio-1.1.3.dist-info/LICENSE
pasio-1.1.3.dist-info/METADATA
pasio-1.1.3.dist-info/MIT-LICENSE
pasio-1.1.3.dist-info/WHEEL
pasio-1.1.3.dist-info/entry_points.txt
pasio-1.1.3.dist-info/top_level.txt
pasio-1.1.3.dist-info/RECORD
