Metadata-Version: 2.1
Name: pasio
Version: 1.1.3
Summary: Pasio is a tool for segmentation and denosing DNA coverage profiles coming from high-throughput sequencing data.
Home-page: https://github.com/autosome-ru/pasio
Author: Andrey Lando, Ilya Vorontsov
Author-email: dronte.l@gmail.com, vorontsov.i.e@gmail.com
License: Pasio is licensed under WTFPL, but if you prefer more standard licenses, feel free to treat it as MIT license
Keywords: bioinformatics NGS coverage segmentation denoise
Platform: UNKNOWN
Classifier: Topic :: Scientific/Engineering :: Bio-Informatics
Classifier: Intended Audience :: Science/Research
Classifier: License :: OSI Approved :: MIT License
Classifier: Development Status :: 5 - Production/Stable
Classifier: Operating System :: OS Independent
Classifier: Programming Language :: Python :: 2
Classifier: Programming Language :: Python :: 2.7
Classifier: Programming Language :: Python :: 3
Classifier: Programming Language :: Python :: 3.4
Classifier: Programming Language :: Python :: 3.5
Classifier: Programming Language :: Python :: 3.6
Classifier: Programming Language :: Python :: 3.7
Classifier: Programming Language :: Python :: 3.8
Requires-Python: >=2.7.1, !=3.0.*, !=3.1.*, !=3.2.*, !=3.3.*
Requires-Dist: numpy (>=1.8.0)
Requires-Dist: scipy (>=0.12.0)
Requires-Dist: future (>=0.4.0)
Provides-Extra: dev
Requires-Dist: pytest ; extra == 'dev'
Requires-Dist: pytest-benchmark ; extra == 'dev'
Requires-Dist: flake8 ; extra == 'dev'
Requires-Dist: tox ; extra == 'dev'
Requires-Dist: wheel ; extra == 'dev'
Requires-Dist: twine ; extra == 'dev'
Requires-Dist: setuptools-scm ; extra == 'dev'
